{
  "ja": [
    {
      "time": "2026-06-15T11:13:47+00:00",
      "title": "サッカー日本代表DF伊藤洋輝、オランダ戦ドローに前向き。守備の対応に手応え【北中米W杯】",
      "body": "フットボールチャンネル",
      "tag": "ニュース",
      "url": "https://www.footballchannel.jp/2026/06/15/post917295/"
    },
    {
      "time": "2026-06-15T11:00:31+00:00",
      "title": "ベルギー代表対エジプト代表、予想スタメン＆フォーメーション【北中米W杯】",
      "body": "フットボールチャンネル",
      "tag": "ニュース",
      "url": "https://www.footballchannel.jp/2026/06/15/post917163/"
    },
    {
      "time": "2026-06-15T10:42:41+00:00",
      "title": "「3を取りに行ってゼロになるより1」 サッカー日本代表DF冨安健洋、オランダ戦ドローをポジティブに総括【北中米W杯】",
      "body": "フットボールチャンネル",
      "tag": "ニュース",
      "url": "https://www.footballchannel.jp/2026/06/15/post917271/"
    },
    {
      "time": "2026-06-15T10:18:11+00:00",
      "title": "なぜ5-1もの大差に？ スウェーデン代表とチュニジア代表。日本代表のライバルが明暗を分けた大きな理由【北中米W杯分析コラム】",
      "body": "フットボールチャンネル",
      "tag": "ニュース",
      "url": "https://www.footballchannel.jp/2026/06/15/post917202/"
    },
    {
      "time": "2026-06-15T10:00:54+00:00",
      "title": "「相手が寄せてこない」日本代表のジョーカー、伊東純也が終盤に見抜いたオランダの綻び【北中米W杯コラム】",
      "body": "フットボールチャンネル",
      "tag": "ニュース",
      "url": "https://www.footballchannel.jp/2026/06/15/post917175/"
    },
    {
      "time": "2026-06-15T10:00:22+00:00",
      "title": "「日本、本当にアジア最強なのか」韓国メディアが日本代表を高評価　強豪オランダ相手に見せた底力【北中米W杯】",
      "body": "フットボールチャンネル",
      "tag": "ニュース",
      "url": "https://www.footballchannel.jp/2026/06/15/post916698/"
    },
    {
      "time": "2026-06-15T09:41:43+00:00",
      "title": "【フランス代表 北中米W杯無料選手名鑑】予想フォーメーション＆招集メンバー全選手徹底紹介",
      "body": "フットボールチャンネル",
      "tag": "ニュース",
      "url": "https://www.footballchannel.jp/2026/06/15/post910467/"
    },
    {
      "time": "2026-06-15T09:40:06+00:00",
      "title": "ウルグアイ代表の注目選手は誰？一撃で流れを変える！？16日にサウジアラビア代表と初戦へ【北中米W杯】",
      "body": "フットボールチャンネル",
      "tag": "ニュース",
      "url": "https://www.footballchannel.jp/2026/06/15/post915690/"
    },
    {
      "time": "2026-06-15T09:19:03+00:00",
      "title": "ククレジャ獲得失敗のアトレティコ、同じスペイン代表SBグリマルドへの動き本格化か",
      "body": "サッカーキング",
      "tag": "ニュース",
      "url": "https://www.soccer-king.jp/news/world/esp/20260615/2172318.html"
    },
    {
      "time": "2026-06-15T09:00:48+00:00",
      "title": "「より強い自信が必要」英メディアが日本代表に指摘　オランダ戦の粘り評価も“メンタリティ”に課題【北中米W杯】",
      "body": "フットボールチャンネル",
      "tag": "ニュース",
      "url": "https://www.footballchannel.jp/2026/06/15/post916680/"
    },
    {
      "time": "2026-06-15T09:00:28+00:00",
      "title": "スペイン代表対カーボベルデ代表、予想スタメン＆フォーメーション【北中米W杯】",
      "body": "フットボールチャンネル",
      "tag": "ニュース",
      "url": "https://www.footballchannel.jp/2026/06/15/post916977/"
    },
    {
      "time": "2026-06-15T08:49:26+00:00",
      "title": "【W杯2026】日本、鎌田大地の劇的同点弾でオランダとドロー！グループFはスウェーデンが5発快勝で首位スタート｜大会4日目結果",
      "body": "ワールドサッカーダイジェスト",
      "tag": "ニュース",
      "url": "https://web.ultra-soccer.jp/news/japan/24401/?utm_source=rss&utm_medium=rss&utm_campaign=%25e3%2580%2590w%25e6%259d%25af2026%25e3%2580%2591%25e6%2597%25a5%25e6%259c%25ac%25e3%2580%2581%25e9%258e%258c%25e7%2594%25b0%25e5%25a4%25a7%25e5%259c%25b0%25e3%2581%25ae%25e5%258a%2587%25e7%259a%2584%25e5%2590%258c%25e7%2582%25b9%25e5%25bc%25be%25e3%2581%25a7%25e3%2582%25aa%25e3%2583%25a9%25e3%2583%25b3%25e3%2583%2580"
    },
    {
      "time": "2026-06-15T07:47:14+00:00",
      "title": "スウェーデンの“至宝”、ベリヴァルが32年ぶり記録更新…同国史上最年少でのW杯出場者に",
      "body": "サッカーキング",
      "tag": "ニュース",
      "url": "https://www.soccer-king.jp/news/world/wc/20260615/2172313.html"
    },
    {
      "time": "2026-06-15T06:52:14+00:00",
      "title": "日本代表に2度追いつかれるも…オランダ代表MFデ・ヨング「いい試合だった」",
      "body": "サッカーキング",
      "tag": "ニュース",
      "url": "https://www.soccer-king.jp/news/world/wc/20260615/2172261.html"
    }
  ],
  "en": [
    {
      "time": "2026-06-14T12:00:00Z",
      "title": "Full-time ⚽",
      "body": "Germany 7-1 Curaçao",
      "tag": "FULL-TIME"
    },
    {
      "time": "2026-06-14T12:00:00Z",
      "title": "Full-time ⚽",
      "body": "Côte d'Ivoire 1-0 Ecuador",
      "tag": "FULL-TIME"
    },
    {
      "time": "2026-06-14T12:00:00Z",
      "title": "Full-time ⚽",
      "body": "Netherlands 2-2 Japan",
      "tag": "FULL-TIME"
    },
    {
      "time": "2026-06-14T12:00:00Z",
      "title": "Full-time ⚽",
      "body": "Sweden 5-1 Tunisia",
      "tag": "FULL-TIME"
    },
    {
      "time": "2026-06-13T12:00:00Z",
      "title": "Full-time ⚽",
      "body": "Qatar 1-1 Switzerland",
      "tag": "FULL-TIME"
    },
    {
      "time": "2026-06-13T12:00:00Z",
      "title": "Full-time ⚽",
      "body": "Brazil 1-1 Morocco",
      "tag": "FULL-TIME"
    },
    {
      "time": "2026-06-13T12:00:00Z",
      "title": "Full-time ⚽",
      "body": "Haiti 0-1 Scotland",
      "tag": "FULL-TIME"
    },
    {
      "time": "2026-06-13T12:00:00Z",
      "title": "Full-time ⚽",
      "body": "Australia 2-0 Türkiye",
      "tag": "FULL-TIME"
    },
    {
      "time": "2026-06-12T12:00:00Z",
      "title": "Full-time ⚽",
      "body": "Canada 1-1 Bosnia & Herzegovina",
      "tag": "FULL-TIME"
    },
    {
      "time": "2026-06-12T12:00:00Z",
      "title": "Full-time ⚽",
      "body": "USA 4-1 Paraguay",
      "tag": "FULL-TIME"
    },
    {
      "time": "2026-06-11T12:00:00Z",
      "title": "Full-time ⚽",
      "body": "Mexico 2-0 South Africa",
      "tag": "FULL-TIME"
    },
    {
      "time": "2026-06-11T12:00:00Z",
      "title": "Full-time ⚽",
      "body": "Korea Republic 2-1 Czechia",
      "tag": "FULL-TIME"
    }
  ]
}