{
  "ja": [
    {
      "time": "2026-06-22T10:33:54+00:00",
      "title": "イラン代表がロッカールームに感謝のメッセージ　ロサンゼルスのもてなしに謝意「誇りとともに去る」",
      "body": "フットボールチャンネル",
      "tag": "ニュース",
      "url": "https://www.footballchannel.jp/2026/06/22/post926532/"
    },
    {
      "time": "2026-06-22T10:02:48+00:00",
      "title": "W杯で脚光浴びる守護神たちも着用！GKグローブ「ELITE SPORT」日本公式サイトが開設",
      "body": "ワールドサッカーダイジェスト",
      "tag": "ニュース",
      "url": "https://web.ultra-soccer.jp/news/domestic/25830/?utm_source=rss&utm_medium=rss&utm_campaign=w%25e6%259d%25af%25e3%2581%25a7%25e8%2584%259a%25e5%2585%2589%25e6%25b5%25b4%25e3%2581%25b3%25e3%2582%258b%25e5%25ae%2588%25e8%25ad%25b7%25e7%25a5%259e%25e3%2581%259f%25e3%2581%25a1%25e3%2582%2582%25e7%259d%2580%25e7%2594%25a8%25ef%25bc%2581gk%25e3%2582%25b0%25e3%2583%25ad%25e3%2583%25bc%25e3%2583%2596%25e3%2580%258celite-sp"
    },
    {
      "time": "2026-06-22T09:58:25+00:00",
      "title": "【6月24日】コロンビア代表 vs コンゴ民主共和国代表｜地上波テレビ放送・中継・ネット配信｜実況・解説｜順位表｜FIFAワールドカップ2026",
      "body": "サッカーキング",
      "tag": "ニュース",
      "url": "https://www.soccer-king.jp/news/world/wc/fixed/2175766.html"
    },
    {
      "time": "2026-06-22T09:54:18+00:00",
      "title": "日本戦でゴールを決めたオランダ代表FW、今夏にステップアップか…CL連覇のPSGも関心？",
      "body": "サッカーキング",
      "tag": "ニュース",
      "url": "https://www.soccer-king.jp/news/world/eng/20260622/2175710.html"
    },
    {
      "time": "2026-06-22T09:50:37+00:00",
      "title": "ウルグアイ代表FWの対応が話題に！？　“フェアプレー精神”と“勝利優先”のはざまで下した判断",
      "body": "フットボールチャンネル",
      "tag": "ニュース",
      "url": "https://www.footballchannel.jp/2026/06/22/post926484/"
    },
    {
      "time": "2026-06-22T09:30:58+00:00",
      "title": "オーストリア代表の最新ユニフォームがかっこいい！ 珍しい発想！？ 23日のアルゼンチン代表戦で着用へ",
      "body": "フットボールチャンネル",
      "tag": "ニュース",
      "url": "https://www.footballchannel.jp/2026/06/22/post926277/"
    },
    {
      "time": "2026-06-22T09:30:31+00:00",
      "title": "W杯グループGの突破争いは混沌…各国の突破条件は？ 強豪ベルギー代表はGL敗退の危機、首位エジプトも突破未確定",
      "body": "フットボールチャンネル",
      "tag": "ニュース",
      "url": "https://www.footballchannel.jp/2026/06/22/post926184/"
    },
    {
      "time": "2026-06-22T09:25:45+00:00",
      "title": "【6月24日】パナマ代表 vs クロアチア代表｜地上波テレビ放送・中継・ネット配信｜実況・解説｜順位表｜FIFAワールドカップ2026",
      "body": "サッカーキング",
      "tag": "ニュース",
      "url": "https://www.soccer-king.jp/news/world/wc/fixed/2175756.html"
    },
    {
      "time": "2026-06-22T09:20:57+00:00",
      "title": "FIFAワールドカップ2026｜出場国一覧｜試合日程・結果・放送・配信・実況・解説｜日本代表",
      "body": "サッカーキング",
      "tag": "ニュース",
      "url": "https://www.soccer-king.jp/news/japan/national/fixed/2101065.html"
    },
    {
      "time": "2026-06-22T09:16:21+00:00",
      "title": "【6月24日】イングランド代表 vs ガーナ代表｜地上波テレビ放送・中継・ネット配信｜実況・解説｜順位表｜FIFAワールドカップ2026",
      "body": "サッカーキング",
      "tag": "ニュース",
      "url": "https://www.soccer-king.jp/news/world/wc/fixed/2175754.html"
    },
    {
      "time": "2026-06-22T09:03:25+00:00",
      "title": "早期敗退のトルコ代表、連盟トップがモンテッラ監督を擁護　現体制支持を強調「引き続き責任を持って支えていく」",
      "body": "フットボールチャンネル",
      "tag": "ニュース",
      "url": "https://www.footballchannel.jp/2026/06/22/post926436/"
    },
    {
      "time": "2026-06-22T09:00:54+00:00",
      "title": "アルゼンチン代表対オーストリア代表、予想スタメン＆フォーメーション！ リオネル・メッシのW杯通算最多ゴール更新に期待",
      "body": "フットボールチャンネル",
      "tag": "ニュース",
      "url": "https://www.footballchannel.jp/2026/06/22/post926358/"
    },
    {
      "time": "2026-06-22T09:00:53+00:00",
      "title": "「まあ嬉しいは嬉しいですね」日本代表、伊東純也は淡々と噛み締めた。森保ジャパンに不可欠な男が抱いていた決意とは【北中米W杯コラム】",
      "body": "フットボールチャンネル",
      "tag": "ニュース",
      "url": "https://www.footballchannel.jp/2026/06/22/post926295/"
    },
    {
      "time": "2026-06-22T08:58:43+00:00",
      "title": "【6月24日】ポルトガル代表 vs ウズベキスタン代表｜地上波テレビ放送・中継・ネット配信｜実況・解説｜順位表｜FIFAワールドカップ2026",
      "body": "サッカーキング",
      "tag": "ニュース",
      "url": "https://www.soccer-king.jp/news/world/wc/fixed/2175744.html"
    }
  ],
  "en": [
    {
      "time": "2026-06-21T12:00:00Z",
      "title": "Full-time ⚽",
      "body": "Belgium 0-0 IR Iran",
      "tag": "FULL-TIME"
    },
    {
      "time": "2026-06-21T12:00:00Z",
      "title": "Full-time ⚽",
      "body": "New Zealand 1-3 Egypt",
      "tag": "FULL-TIME"
    },
    {
      "time": "2026-06-21T12:00:00Z",
      "title": "Full-time ⚽",
      "body": "Spain 4-0 Saudi Arabia",
      "tag": "FULL-TIME"
    },
    {
      "time": "2026-06-21T12:00:00Z",
      "title": "Full-time ⚽",
      "body": "Uruguay 2-2 Cabo Verde",
      "tag": "FULL-TIME"
    },
    {
      "time": "2026-06-20T12:00:00Z",
      "title": "Full-time ⚽",
      "body": "Germany 2-1 Côte d'Ivoire",
      "tag": "FULL-TIME"
    },
    {
      "time": "2026-06-20T12:00:00Z",
      "title": "Full-time ⚽",
      "body": "Ecuador 0-0 Curaçao",
      "tag": "FULL-TIME"
    },
    {
      "time": "2026-06-20T12:00:00Z",
      "title": "Full-time ⚽",
      "body": "Netherlands 5-1 Sweden",
      "tag": "FULL-TIME"
    },
    {
      "time": "2026-06-20T12:00:00Z",
      "title": "Full-time ⚽",
      "body": "Tunisia 0-4 Japan",
      "tag": "FULL-TIME"
    },
    {
      "time": "2026-06-19T12:00:00Z",
      "title": "Full-time ⚽",
      "body": "Scotland 0-1 Morocco",
      "tag": "FULL-TIME"
    },
    {
      "time": "2026-06-19T12:00:00Z",
      "title": "Full-time ⚽",
      "body": "Brazil 3-0 Haiti",
      "tag": "FULL-TIME"
    },
    {
      "time": "2026-06-19T12:00:00Z",
      "title": "Full-time ⚽",
      "body": "USA 2-0 Australia",
      "tag": "FULL-TIME"
    },
    {
      "time": "2026-06-19T12:00:00Z",
      "title": "Full-time ⚽",
      "body": "Türkiye 0-1 Paraguay",
      "tag": "FULL-TIME"
    }
  ]
}