{
  "ja": [
    {
      "time": "2026-07-07T09:00:24+00:00",
      "title": "アルゼンチン代表対エジプト代表、予想スタメン＆フォーメーション！ メッシとサラーが激突へ",
      "body": "フットボールチャンネル",
      "tag": "ニュース",
      "url": "https://www.footballchannel.jp/2026/07/07/post942474/"
    },
    {
      "time": "2026-07-07T08:58:53+00:00",
      "title": "ポルトガル代表FWペドロ・ネトが”穴あきスパイク”でプレー。履き替えた予備にも同じ加工",
      "body": "フットボールチャンネル",
      "tag": "ニュース",
      "url": "https://www.footballchannel.jp/2026/07/07/post942498/"
    },
    {
      "time": "2026-07-07T08:14:08+00:00",
      "title": "渦中のアメリカ代表FWバログン、メンタル面が影響？ 議論の中心となった一戦でスタッツが示した苦戦",
      "body": "フットボールチャンネル",
      "tag": "ニュース",
      "url": "https://www.footballchannel.jp/2026/07/07/post942492/"
    },
    {
      "time": "2026-07-07T08:02:11+00:00",
      "title": "ベスト16で敗退のアメリカ代表、ピッチ外の騒動に揺れるも「影響はなかった」と口を揃える",
      "body": "ワールドサッカーダイジェスト",
      "tag": "ニュース",
      "url": "https://web.ultra-soccer.jp/news/all/28397/?utm_source=rss&utm_medium=rss&utm_campaign=%25e3%2583%2599%25e3%2582%25b9%25e3%2583%258816%25e3%2581%25a7%25e6%2595%2597%25e9%2580%2580%25e3%2581%25ae%25e3%2582%25a2%25e3%2583%25a1%25e3%2583%25aa%25e3%2582%25ab%25e4%25bb%25a3%25e8%25a1%25a8%25e3%2580%2581%25e3%2583%2594%25e3%2583%2583%25e3%2583%2581%25e5%25a4%2596%25e3%2581%25ae%25e9%25a8%2592%25e5%258b%2595%25e3%2581%25ab"
    },
    {
      "time": "2026-07-07T07:14:51+00:00",
      "title": "難敵撃破で4大会ぶり準々決勝進出も…スペイン代表MFロドリ「現状に満足して足を止めるわけにはいかない」",
      "body": "ワールドサッカーダイジェスト",
      "tag": "ニュース",
      "url": "https://web.ultra-soccer.jp/news/all/28385/?utm_source=rss&utm_medium=rss&utm_campaign=%25e9%259b%25a3%25e6%2595%25b5%25e6%2592%2583%25e7%25a0%25b4%25e3%2581%25a74%25e5%25a4%25a7%25e4%25bc%259a%25e3%2581%25b6%25e3%2582%258a%25e6%25ba%2596%25e3%2580%2585%25e6%25b1%25ba%25e5%258b%259d%25e9%2580%25b2%25e5%2587%25ba%25e3%2582%2582%25e3%2582%25b9%25e3%2583%259a%25e3%2582%25a4%25e3%2583%25b3%25e4%25bb%25a3"
    },
    {
      "time": "2026-07-07T06:07:13+00:00",
      "title": "41歳C・ロナウド「今大会は僕にとって最後のW杯」　ポルトガル代表として6度目の挑戦は16強敗退",
      "body": "ワールドサッカーダイジェスト",
      "tag": "ニュース",
      "url": "https://web.ultra-soccer.jp/news/all/28379/?utm_source=rss&utm_medium=rss&utm_campaign=41%25e6%25ad%25b3c%25e3%2583%25bb%25e3%2583%25ad%25e3%2583%258a%25e3%2582%25a6%25e3%2583%2589%25e3%2580%258c%25e4%25bb%258a%25e5%25a4%25a7%25e4%25bc%259a%25e3%2581%25af%25e5%2583%2595%25e3%2581%25ab%25e3%2581%25a8%25e3%2581%25a3%25e3%2581%25a6%25e6%259c%2580%25e5%25be%258c%25e3%2581%25aew%25e6%259d%25af%25e3%2580%258d"
    },
    {
      "time": "2026-07-07T05:35:55+00:00",
      "title": "ポルトガル、スペインに敗れW杯16強敗退…指揮官は退任を明言「一つのサイクルが終わった」",
      "body": "ワールドサッカーダイジェスト",
      "tag": "ニュース",
      "url": "https://web.ultra-soccer.jp/news/all/28382/?utm_source=rss&utm_medium=rss&utm_campaign=%25e3%2583%259d%25e3%2583%25ab%25e3%2583%2588%25e3%2582%25ac%25e3%2583%25ab%25e3%2580%2581%25e3%2582%25b9%25e3%2583%259a%25e3%2582%25a4%25e3%2583%25b3%25e3%2581%25ab%25e6%2595%2597%25e3%2582%258cw%25e6%259d%25af16%25e5%25bc%25b7%25e6%2595%2597%25e9%2580%2580%25e6%258c%2587%25e6%258f%25ae%25e5%25ae%2598"
    },
    {
      "time": "2026-07-07T05:23:14+00:00",
      "title": "｢こんな一体感のあるチームないぞ｣日本代表、ブラジル戦のロッカールームの様子を投稿。板倉滉キャプテンの円陣も",
      "body": "フットボールチャンネル",
      "tag": "ニュース",
      "url": "https://www.footballchannel.jp/2026/07/07/post942399/"
    },
    {
      "time": "2026-07-07T04:32:12+00:00",
      "title": "前回王者相手に決めた最高の一撃！ カーボベルデ代表DFの得点がラウンド32のベストゴールに選出",
      "body": "フットボールチャンネル",
      "tag": "ニュース",
      "url": "https://www.footballchannel.jp/2026/07/07/post942387/"
    },
    {
      "time": "2026-07-07T03:51:28+00:00",
      "title": "大躍進の英雄たちを歓迎！ カーボベルデ代表の選手たちがW杯から帰国後にパレードを実施。サポーターたちはお祭り騒ぎ",
      "body": "フットボールチャンネル",
      "tag": "ニュース",
      "url": "https://www.footballchannel.jp/2026/07/07/post942375/"
    },
    {
      "time": "2026-07-07T03:42:13+00:00",
      "title": "アメリカ代表は史上最も応援されない開催国に？ 公平性を揺るがせた異例の決定。世界中を敵に回した国のあっけない結末",
      "body": "フットボールチャンネル",
      "tag": "ニュース",
      "url": "https://www.footballchannel.jp/2026/07/07/post942354/"
    },
    {
      "time": "2026-07-07T02:31:44+00:00",
      "title": "ワールドカップ全試合の日程・結果・放送予定一覧。視聴方法・キックオフ時間　北中米W杯",
      "body": "フットボールチャンネル",
      "tag": "ニュース",
      "url": "https://www.footballchannel.jp/2026/07/07/post816645/"
    },
    {
      "time": "2026-07-06T12:00:00Z",
      "title": "試合終了 ⚽",
      "body": "ポルトガル 0-1 スペイン",
      "tag": "試合終了"
    },
    {
      "time": "2026-07-06T12:00:00Z",
      "title": "試合終了 ⚽",
      "body": "アメリカ 1-4 ベルギー",
      "tag": "試合終了"
    }
  ],
  "en": [
    {
      "time": "2026-07-06T12:00:00Z",
      "title": "Full-time ⚽",
      "body": "Portugal 0-1 Spain",
      "tag": "FULL-TIME"
    },
    {
      "time": "2026-07-06T12:00:00Z",
      "title": "Full-time ⚽",
      "body": "USA 1-4 Belgium",
      "tag": "FULL-TIME"
    },
    {
      "time": "2026-07-05T12:00:00Z",
      "title": "Full-time ⚽",
      "body": "Brazil 1-2 Norway",
      "tag": "FULL-TIME"
    },
    {
      "time": "2026-07-05T12:00:00Z",
      "title": "Full-time ⚽",
      "body": "Mexico 2-3 England",
      "tag": "FULL-TIME"
    },
    {
      "time": "2026-07-04T12:00:00Z",
      "title": "Full-time ⚽",
      "body": "Paraguay 0-1 France",
      "tag": "FULL-TIME"
    },
    {
      "time": "2026-07-04T12:00:00Z",
      "title": "Full-time ⚽",
      "body": "Canada 0-3 Morocco",
      "tag": "FULL-TIME"
    },
    {
      "time": "2026-07-03T12:00:00Z",
      "title": "Full-time ⚽",
      "body": "Argentina 1-1 Cabo Verde",
      "tag": "FULL-TIME"
    },
    {
      "time": "2026-07-03T12:00:00Z",
      "title": "Full-time ⚽",
      "body": "Colombia 1-0 Ghana",
      "tag": "FULL-TIME"
    },
    {
      "time": "2026-07-03T12:00:00Z",
      "title": "Full-time ⚽",
      "body": "Australia 1-1 Egypt",
      "tag": "FULL-TIME"
    },
    {
      "time": "2026-07-02T12:00:00Z",
      "title": "Full-time ⚽",
      "body": "Portugal 2-1 Croatia",
      "tag": "FULL-TIME"
    },
    {
      "time": "2026-07-02T12:00:00Z",
      "title": "Full-time ⚽",
      "body": "Spain 3-0 Austria",
      "tag": "FULL-TIME"
    },
    {
      "time": "2026-07-02T12:00:00Z",
      "title": "Full-time ⚽",
      "body": "Switzerland 2-0 Algeria",
      "tag": "FULL-TIME"
    }
  ]
}