{
  "ja": [
    {
      "time": "2026-07-05T14:27:41+00:00",
      "title": "マンUがチェルシーのブラジル代表MFに関心…A・サントスの評価額は約107億円か",
      "body": "ワールドサッカーダイジェスト",
      "tag": "ニュース",
      "url": "https://web.ultra-soccer.jp/news/all/28092/?utm_source=rss&utm_medium=rss&utm_campaign=%25e3%2583%259e%25e3%2583%25b3u%25e3%2581%258c%25e3%2583%2581%25e3%2582%25a7%25e3%2583%25ab%25e3%2582%25b7%25e3%2583%25bc%25e3%2581%25ae%25e3%2583%2596%25e3%2583%25a9%25e3%2582%25b8%25e3%2583%25ab%25e4%25bb%25a3%25e8%25a1%25a8mf%25e3%2581%25ab%25e9%2596%25a2%25e5%25bf%2583a%25e3%2583%25bb%25e3%2582%25b5"
    },
    {
      "time": "2026-07-05T13:29:56+00:00",
      "title": "ブラジル代表、W杯決勝トーナメントのvs欧州勢は“鬼門”…20年未勝利のジンクスをノルウェー戦で打破できるのか",
      "body": "ワールドサッカーダイジェスト",
      "tag": "ニュース",
      "url": "https://web.ultra-soccer.jp/news/all/28089/?utm_source=rss&utm_medium=rss&utm_campaign=%25e3%2583%2596%25e3%2583%25a9%25e3%2582%25b8%25e3%2583%25ab%25e4%25bb%25a3%25e8%25a1%25a8%25e3%2580%2581w%25e6%259d%25af%25e6%25b1%25ba%25e5%258b%259d%25e3%2583%2588%25e3%2583%25bc%25e3%2583%258a%25e3%2583%25a1%25e3%2583%25b3%25e3%2583%2588%25e3%2581%25aevs%25e6%25ac%25a7%25e5%25b7%259e%25e5%258b%25a2%25e3%2581%25af"
    },
    {
      "time": "2026-07-05T12:46:39+00:00",
      "title": "【写真ギャラリー】2026.7.4 FIFAワールドカップ2026 決勝トーナメント2回戦（ラウンド16） パラグアイ代表 0－1 フランス代表",
      "body": "ワールドサッカーダイジェスト",
      "tag": "ニュース",
      "url": "https://web.ultra-soccer.jp/news/all/28078/?utm_source=rss&utm_medium=rss&utm_campaign=%25e3%2580%2590%25e5%2586%2599%25e7%259c%259f%25e3%2582%25ae%25e3%2583%25a3%25e3%2583%25a9%25e3%2583%25aa%25e3%2583%25bc%25e3%2580%25912026-7-4-fifa%25e3%2583%25af%25e3%2583%25bc%25e3%2583%25ab%25e3%2583%2589%25e3%2582%25ab%25e3%2583%2583%25e3%2583%25972026-%25e6%25b1%25ba%25e5%258b%259d%25e3%2583%2588%25e3%2583%25bc"
    },
    {
      "time": "2026-07-05T12:39:21+00:00",
      "title": "【7月7日】アメリカ代表 vs ベルギー代表｜地上波テレビ放送・中継・ネット配信｜実況・解説｜順位表｜FIFAワールドカップ2026",
      "body": "ワールドサッカーダイジェスト",
      "tag": "ニュース",
      "url": "https://web.ultra-soccer.jp/news/all/28084/?utm_source=rss&utm_medium=rss&utm_campaign=%25e3%2580%25907%25e6%259c%25887%25e6%2597%25a5%25e3%2580%2591%25e3%2582%25a2%25e3%2583%25a1%25e3%2583%25aa%25e3%2582%25ab%25e4%25bb%25a3%25e8%25a1%25a8-vs-%25e3%2583%2599%25e3%2583%25ab%25e3%2582%25ae%25e3%2583%25bc%25e4%25bb%25a3%25e8%25a1%25a8%25ef%25bd%259c%25e5%259c%25b0%25e4%25b8%258a%25e6%25b3%25a2%25e3%2583%2586"
    },
    {
      "time": "2026-07-05T12:03:28+00:00",
      "title": "【7月7日】ポルトガル代表 vs スペイン代表｜地上波テレビ放送・中継・ネット配信｜実況・解説｜順位表｜FIFAワールドカップ2026",
      "body": "ワールドサッカーダイジェスト",
      "tag": "ニュース",
      "url": "https://web.ultra-soccer.jp/news/all/28072/?utm_source=rss&utm_medium=rss&utm_campaign=%25e3%2580%25907%25e6%259c%25887%25e6%2597%25a5%25e3%2580%2591%25e3%2583%259d%25e3%2583%25ab%25e3%2583%2588%25e3%2582%25ac%25e3%2583%25ab%25e4%25bb%25a3%25e8%25a1%25a8-vs-%25e3%2582%25b9%25e3%2583%259a%25e3%2582%25a4%25e3%2583%25b3%25e4%25bb%25a3%25e8%25a1%25a8%25ef%25bd%259c%25e5%259c%25b0%25e4%25b8%258a%25e6%25b3%25a2"
    },
    {
      "time": "2026-07-05T11:49:56+00:00",
      "title": "ドルトムント、今夏の来日ツアーにドイツ代表3選手も帯同へ…W杯早期敗退で日本から合流か",
      "body": "ワールドサッカーダイジェスト",
      "tag": "ニュース",
      "url": "https://web.ultra-soccer.jp/news/all/28075/?utm_source=rss&utm_medium=rss&utm_campaign=%25e3%2583%2589%25e3%2583%25ab%25e3%2583%2588%25e3%2583%25a0%25e3%2583%25b3%25e3%2583%2588%25e3%2580%2581%25e4%25bb%258a%25e5%25a4%258f%25e3%2581%25ae%25e6%259d%25a5%25e6%2597%25a5%25e3%2583%2584%25e3%2582%25a2%25e3%2583%25bc%25e3%2581%25ab%25e3%2583%2589%25e3%2582%25a4%25e3%2583%2584%25e4%25bb%25a3%25e8%25a1%25a83%25e9%2581%25b8"
    },
    {
      "time": "2026-07-05T11:00:42+00:00",
      "title": "メキシコ代表の最新ユニフォームがかっこいい！ 神殿や壁画から着想！？ 6日のイングランド代表戦で着用へ",
      "body": "フットボールチャンネル",
      "tag": "ニュース",
      "url": "https://www.footballchannel.jp/2026/07/05/post909939/"
    },
    {
      "time": "2026-07-05T10:42:15+00:00",
      "title": "レアル、オランダ代表DFダンフリースの獲得を発表！　今夏4人目の新戦力と4年契約締結",
      "body": "ワールドサッカーダイジェスト",
      "tag": "ニュース",
      "url": "https://web.ultra-soccer.jp/news/all/28069/?utm_source=rss&utm_medium=rss&utm_campaign=%25e3%2583%25ac%25e3%2582%25a2%25e3%2583%25ab%25e3%2580%2581%25e3%2582%25aa%25e3%2583%25a9%25e3%2583%25b3%25e3%2583%2580%25e4%25bb%25a3%25e8%25a1%25a8df%25e3%2583%2580%25e3%2583%25b3%25e3%2583%2595%25e3%2583%25aa%25e3%2583%25bc%25e3%2582%25b9%25e3%2581%25ae%25e7%258d%25b2%25e5%25be%2597%25e3%2582%2592%25e7%2599%25ba%25e8%25a1%25a8"
    },
    {
      "time": "2026-07-05T09:42:56+00:00",
      "title": "「適応することはできない」イングランド代表指揮官、標高2240ｍの戦いに本音も「歴史を刻むためにここにいる」",
      "body": "ワールドサッカーダイジェスト",
      "tag": "ニュース",
      "url": "https://web.ultra-soccer.jp/news/all/28063/?utm_source=rss&utm_medium=rss&utm_campaign=%25e3%2580%258c%25e9%2581%25a9%25e5%25bf%259c%25e3%2581%2599%25e3%2582%258b%25e3%2581%2593%25e3%2581%25a8%25e3%2581%25af%25e3%2581%25a7%25e3%2581%258d%25e3%2581%25aa%25e3%2581%2584%25e3%2580%258d%25e3%2582%25a4%25e3%2583%25b3%25e3%2582%25b0%25e3%2583%25a9%25e3%2583%25b3%25e3%2583%2589%25e4%25bb%25a3%25e8%25a1%25a8%25e6%258c%2587"
    },
    {
      "time": "2026-07-05T09:04:47+00:00",
      "title": "北中米W杯、エースが輝くのはなぜ？ 走行距離にみる「ヒーローの輝かせ方」",
      "body": "フットボールチャンネル",
      "tag": "ニュース",
      "url": "https://www.footballchannel.jp/2026/07/05/post940917/"
    },
    {
      "time": "2026-07-05T09:00:46+00:00",
      "title": "ノルウェー代表の最新ユニフォームがかっこいい！ 斬新！？ まるで国旗そのもの。6日のブラジル代表戦で着用へ",
      "body": "フットボールチャンネル",
      "tag": "ニュース",
      "url": "https://www.footballchannel.jp/2026/07/05/post940764/"
    },
    {
      "time": "2026-07-05T09:00:41+00:00",
      "title": "W杯得点王争いは“ハイレベル”な戦いに　メッシとエムバペが7得点で首位タイ、ケインやハーランドが追走",
      "body": "フットボールチャンネル",
      "tag": "ニュース",
      "url": "https://www.footballchannel.jp/2026/07/05/post940665/"
    },
    {
      "time": "2026-07-05T08:30:43+00:00",
      "title": "「韓国代表は終わった！」中国メディアがFIFAランク急落の韓国に痛烈指摘　韓国メディアも嘆き「日本との格差はなぜ広がるのか」",
      "body": "フットボールチャンネル",
      "tag": "ニュース",
      "url": "https://www.footballchannel.jp/2026/07/05/post940662/"
    },
    {
      "time": "2026-07-05T07:00:32+00:00",
      "title": "ブラジル代表の最新ユニフォームがかっこいい！ 異例のジョーダンコラボが実現！ 6日のノルウェー代表戦で着用へ",
      "body": "フットボールチャンネル",
      "tag": "ニュース",
      "url": "https://www.footballchannel.jp/2026/07/05/post940752/"
    }
  ],
  "en": [
    {
      "time": "2026-07-04T12:00:00Z",
      "title": "Full-time ⚽",
      "body": "Paraguay 0-1 France",
      "tag": "FULL-TIME"
    },
    {
      "time": "2026-07-04T12:00:00Z",
      "title": "Full-time ⚽",
      "body": "Canada 0-3 Morocco",
      "tag": "FULL-TIME"
    },
    {
      "time": "2026-07-03T12:00:00Z",
      "title": "Full-time ⚽",
      "body": "Argentina 1-1 Cabo Verde",
      "tag": "FULL-TIME"
    },
    {
      "time": "2026-07-03T12:00:00Z",
      "title": "Full-time ⚽",
      "body": "Colombia 1-0 Ghana",
      "tag": "FULL-TIME"
    },
    {
      "time": "2026-07-03T12:00:00Z",
      "title": "Full-time ⚽",
      "body": "Australia 1-1 Egypt",
      "tag": "FULL-TIME"
    },
    {
      "time": "2026-07-02T12:00:00Z",
      "title": "Full-time ⚽",
      "body": "Portugal 2-1 Croatia",
      "tag": "FULL-TIME"
    },
    {
      "time": "2026-07-02T12:00:00Z",
      "title": "Full-time ⚽",
      "body": "Spain 3-0 Austria",
      "tag": "FULL-TIME"
    },
    {
      "time": "2026-07-02T12:00:00Z",
      "title": "Full-time ⚽",
      "body": "Switzerland 2-0 Algeria",
      "tag": "FULL-TIME"
    },
    {
      "time": "2026-07-01T12:00:00Z",
      "title": "Full-time ⚽",
      "body": "England 2-1 DR Congo",
      "tag": "FULL-TIME"
    },
    {
      "time": "2026-07-01T12:00:00Z",
      "title": "Full-time ⚽",
      "body": "USA 2-0 Bosnia & Herzegovina",
      "tag": "FULL-TIME"
    },
    {
      "time": "2026-07-01T12:00:00Z",
      "title": "Full-time ⚽",
      "body": "Belgium 2-2 Senegal",
      "tag": "FULL-TIME"
    },
    {
      "time": "2026-06-30T12:00:00Z",
      "title": "Full-time ⚽",
      "body": "France 3-0 Sweden",
      "tag": "FULL-TIME"
    }
  ]
}