{
  "ja": [
    {
      "time": "2026-06-15T05:14:08+00:00",
      "title": "「みんなの共通意識があったと思う」鎌田大地、サッカー日本代表の準備力と一体感に自信【北中米W杯】",
      "body": "フットボールチャンネル",
      "tag": "ニュース",
      "url": "https://www.footballchannel.jp/2026/06/15/post916851/"
    },
    {
      "time": "2026-06-15T05:01:53+00:00",
      "title": "元Jリーガーが分析。オランダ代表目線の「日本代表戦のリアル」とは。クーマンは何を失敗したのか【田中裕介のMatch dive】",
      "body": "フットボールチャンネル",
      "tag": "ニュース",
      "url": "https://www.footballchannel.jp/2026/06/15/post916659/"
    },
    {
      "time": "2026-06-15T04:56:43+00:00",
      "title": "日本代表、土壇場同点ゴールの凄さは数字にも。スタメン平均身長は6.4cm差。小川航基とファン・ダイクは9cm差【北中米W杯】",
      "body": "フットボールチャンネル",
      "tag": "ニュース",
      "url": "https://www.footballchannel.jp/2026/06/15/post916812/"
    },
    {
      "time": "2026-06-15T04:49:05+00:00",
      "title": "「個人的には全然…」日本代表、佐野海舟がW杯デビュー戦に厳しい自己評価「もっと自分のできることを…」【北中米W杯】",
      "body": "フットボールチャンネル",
      "tag": "ニュース",
      "url": "https://www.footballchannel.jp/2026/06/15/post916806/"
    },
    {
      "time": "2026-06-15T04:38:50+00:00",
      "title": "日本代表はオランダ代表とドロー。スウェーデン代表が白星発進！ ドイツが7ゴールで大勝【北中米W杯／15日結果まとめ】",
      "body": "フットボールチャンネル",
      "tag": "ニュース",
      "url": "https://www.footballchannel.jp/2026/06/15/post916779/"
    },
    {
      "time": "2026-06-15T04:36:31+00:00",
      "title": "「打つ5秒前ぐらいから、あれやるなって」 サッカー日本代表MF伊東純也、中村敬斗の同点弾を“予感”していた【北中米W杯】",
      "body": "フットボールチャンネル",
      "tag": "ニュース",
      "url": "https://www.footballchannel.jp/2026/06/15/post916776/"
    },
    {
      "time": "2026-06-15T04:30:57+00:00",
      "title": "FIFAワールドカップ2026｜出場国一覧｜試合日程・結果・放送・配信・実況・解説｜日本代表",
      "body": "サッカーキング",
      "tag": "ニュース",
      "url": "https://www.soccer-king.jp/news/japan/national/fixed/2101065.html"
    },
    {
      "time": "2026-06-15T04:19:34+00:00",
      "title": "【得点ランキング】FIFAワールドカップ2026　北中米W杯　ゴール数一覧",
      "body": "フットボールチャンネル",
      "tag": "ニュース",
      "url": "https://www.footballchannel.jp/2026/06/15/post909069/"
    },
    {
      "time": "2026-06-15T04:00:22+00:00",
      "title": "ベルギー代表の注目選手は誰？今なお輝く世界屈指の司令塔！16日にエジプト代表と初戦へ【北中米W杯】",
      "body": "フットボールチャンネル",
      "tag": "ニュース",
      "url": "https://www.footballchannel.jp/2026/06/15/post915675/"
    },
    {
      "time": "2026-06-15T03:59:36+00:00",
      "title": "＜結果速報＞スウェーデン代表が5ゴールで白星スタート！ チュニジア代表に5-1で初戦勝利【北中米W杯】",
      "body": "フットボールチャンネル",
      "tag": "ニュース",
      "url": "https://www.footballchannel.jp/2026/06/15/post916734/"
    },
    {
      "time": "2026-06-15T03:59:23+00:00",
      "title": "「どこか“イタリア的”だった」海外記者が日本代表を分析。「ベストプレーヤー」と評したのは？【北中米W杯】",
      "body": "フットボールチャンネル",
      "tag": "ニュース",
      "url": "https://www.footballchannel.jp/2026/06/15/post916704/"
    },
    {
      "time": "2026-06-15T03:42:22+00:00",
      "title": "【写真ギャラリー】2026.6.14 FIFAワールドカップ2026 GS第1節 グループF オランダ代表 2－2 日本代表",
      "body": "サッカーキング",
      "tag": "ニュース",
      "url": "https://www.soccer-king.jp/news/japan/national/20260615/2172109.html"
    },
    {
      "time": "2026-06-15T03:26:03+00:00",
      "title": "日本に土壇場で追いつかれたオランダ、優勝経験なしも60年前樹立のW杯連続無敗記録に並ぶ",
      "body": "サッカーキング",
      "tag": "ニュース",
      "url": "https://www.soccer-king.jp/news/world/wc/20260615/2172106.html"
    },
    {
      "time": "2026-06-15T03:08:03+00:00",
      "title": "日本代表ベンチの“ホワイトボード活用術”に各国注目「即興で工夫した」「残り時間を正確に示すボード」",
      "body": "サッカーキング",
      "tag": "ニュース",
      "url": "https://www.soccer-king.jp/news/japan/national/20260615/2172102.html"
    }
  ],
  "en": [
    {
      "time": "2026-06-14T12:00:00Z",
      "title": "Full-time ⚽",
      "body": "Germany 7-1 Curaçao",
      "tag": "FULL-TIME"
    },
    {
      "time": "2026-06-14T12:00:00Z",
      "title": "Full-time ⚽",
      "body": "Côte d'Ivoire 1-0 Ecuador",
      "tag": "FULL-TIME"
    },
    {
      "time": "2026-06-14T12:00:00Z",
      "title": "Full-time ⚽",
      "body": "Netherlands 2-2 Japan",
      "tag": "FULL-TIME"
    },
    {
      "time": "2026-06-14T12:00:00Z",
      "title": "Full-time ⚽",
      "body": "Sweden 5-1 Tunisia",
      "tag": "FULL-TIME"
    },
    {
      "time": "2026-06-13T12:00:00Z",
      "title": "Full-time ⚽",
      "body": "Qatar 1-1 Switzerland",
      "tag": "FULL-TIME"
    },
    {
      "time": "2026-06-13T12:00:00Z",
      "title": "Full-time ⚽",
      "body": "Brazil 1-1 Morocco",
      "tag": "FULL-TIME"
    },
    {
      "time": "2026-06-13T12:00:00Z",
      "title": "Full-time ⚽",
      "body": "Haiti 0-1 Scotland",
      "tag": "FULL-TIME"
    },
    {
      "time": "2026-06-13T12:00:00Z",
      "title": "Full-time ⚽",
      "body": "Australia 2-0 Türkiye",
      "tag": "FULL-TIME"
    },
    {
      "time": "2026-06-12T12:00:00Z",
      "title": "Full-time ⚽",
      "body": "Canada 1-1 Bosnia & Herzegovina",
      "tag": "FULL-TIME"
    },
    {
      "time": "2026-06-12T12:00:00Z",
      "title": "Full-time ⚽",
      "body": "USA 4-1 Paraguay",
      "tag": "FULL-TIME"
    },
    {
      "time": "2026-06-11T12:00:00Z",
      "title": "Full-time ⚽",
      "body": "Mexico 2-0 South Africa",
      "tag": "FULL-TIME"
    },
    {
      "time": "2026-06-11T12:00:00Z",
      "title": "Full-time ⚽",
      "body": "Korea Republic 2-1 Czechia",
      "tag": "FULL-TIME"
    }
  ]
}