{
  "ja": [
    {
      "time": "2026-06-30T08:01:45+00:00",
      "title": "「まるでイタリアの監督のよう」イブラヒモビッチがクーマン監督を痛烈批判！ オランダ代表敗退に海外メディアも厳しい評価",
      "body": "フットボールチャンネル",
      "tag": "ニュース",
      "url": "https://www.footballchannel.jp/2026/06/30/post936609/"
    },
    {
      "time": "2026-06-30T08:01:35+00:00",
      "title": "ブラジルに「大健闘」の評価に違和感。現役Jリーグ監督が「胸を張って帰ってくる」前に日本代表にやってほしかったこと【後編】",
      "body": "フットボールチャンネル",
      "tag": "ニュース",
      "url": "https://www.footballchannel.jp/2026/06/30/post936597/"
    },
    {
      "time": "2026-06-30T08:01:06+00:00",
      "title": "「いつか失点するよね」現役Jリーグ監督が指摘するブラジル戦、日本代表が「ワールドクラスじゃなかった」こと【前編】",
      "body": "フットボールチャンネル",
      "tag": "ニュース",
      "url": "https://www.footballchannel.jp/2026/06/30/post936567/"
    },
    {
      "time": "2026-06-30T08:00:26+00:00",
      "title": "ここまで準備しても届かなかった日本代表。W杯ベスト32敗退が突きつけた「次の4年」の課題",
      "body": "フットボールチャンネル",
      "tag": "ニュース",
      "url": "https://www.footballchannel.jp/2026/06/30/post936564/"
    },
    {
      "time": "2026-06-30T07:28:43+00:00",
      "title": "「ガムが投げ込まれる場面も」韓国代表がW杯敗退後に帰国…空港は異例の緊張感",
      "body": "フットボールチャンネル",
      "tag": "ニュース",
      "url": "https://www.footballchannel.jp/2026/06/30/post936558/"
    },
    {
      "time": "2026-06-30T07:00:37+00:00",
      "title": "日本代表、ブラジルを上回った3つの“個”。世界最高峰の名手らに匹敵する力。世界一を目指すための基準",
      "body": "フットボールチャンネル",
      "tag": "ニュース",
      "url": "https://www.footballchannel.jp/2026/06/30/post936297/"
    },
    {
      "time": "2026-06-30T06:33:42+00:00",
      "title": "ブラジル代表FWエンドリッキ「まったく予想していなかった」 日本代表戦で後半からの出番に驚き",
      "body": "フットボールチャンネル",
      "tag": "ニュース",
      "url": "https://www.footballchannel.jp/2026/06/30/post936504/"
    },
    {
      "time": "2026-06-30T05:58:38+00:00",
      "title": "「その時々の音楽に合わせて踊るようなもの」パラグアイ代表指揮官、ドイツ撃破後に名言連発！「血と理想が混ざり合った勝利」",
      "body": "フットボールチャンネル",
      "tag": "ニュース",
      "url": "https://www.footballchannel.jp/2026/06/30/post936483/"
    },
    {
      "time": "2026-06-30T05:40:29+00:00",
      "title": "【W杯2026】日本、ブラジルに逆転負けでベスト32敗退…オランダ、ドイツはPK戦で敗戦｜大会19日目結果",
      "body": "ワールドサッカーダイジェスト",
      "tag": "ニュース",
      "url": "https://web.ultra-soccer.jp/news/world/27318/?utm_source=rss&utm_medium=rss&utm_campaign=%25e3%2580%2590w%25e6%259d%25af2026%25e3%2580%2591%25e6%2597%25a5%25e6%259c%25ac%25e4%25bb%25a3%25e8%25a1%25a8%25e3%2580%2581%25e3%2583%2596%25e3%2583%25a9%25e3%2582%25b8%25e3%2583%25ab%25e3%2581%25ab%25e9%2580%2586%25e8%25bb%25a2%25e8%25b2%25a0%25e3%2581%2591%25e3%2581%25a7%25e3%2583%2599%25e3%2582%25b9%25e3%2583%258832"
    },
    {
      "time": "2026-06-30T05:07:03+00:00",
      "title": "北中米W杯が暴いた選手層の薄さ。日本代表がアジアカップで埋めるべきポジションは？",
      "body": "フットボールチャンネル",
      "tag": "ニュース",
      "url": "https://www.footballchannel.jp/2026/06/30/post936459/"
    },
    {
      "time": "2026-06-30T04:57:53+00:00",
      "title": "またも早期敗退のドイツ代表…ナーゲルスマン監督は続投へ意欲「逃げ出すような人間ではない」",
      "body": "ワールドサッカーダイジェスト",
      "tag": "ニュース",
      "url": "https://web.ultra-soccer.jp/news/all/27324/?utm_source=rss&utm_medium=rss&utm_campaign=%25e3%2581%25be%25e3%2581%259f%25e3%2582%2582%25e6%2597%25a9%25e6%259c%259f%25e6%2595%2597%25e9%2580%2580%25e3%2581%25ae%25e3%2583%2589%25e3%2582%25a4%25e3%2583%2584%25e4%25bb%25a3%25e8%25a1%25a8%25e3%2583%258a%25e3%2583%25bc%25e3%2582%25b2%25e3%2583%25ab%25e3%2582%25b9%25e3%2583%259e%25e3%2583%25b3%25e7%259b%25a3"
    },
    {
      "time": "2026-06-30T03:56:07+00:00",
      "title": "【写真ギャラリー】2026.6.29 FIFAワールドカップ2026 決勝トーナメント1回戦（ラウンド32） ブラジル代表 2－1 日本代表",
      "body": "ワールドサッカーダイジェスト",
      "tag": "ニュース",
      "url": "https://web.ultra-soccer.jp/news/all/27306/?utm_source=rss&utm_medium=rss&utm_campaign=%25e3%2580%2590%25e5%2586%2599%25e7%259c%259f%25e3%2582%25ae%25e3%2583%25a3%25e3%2583%25a9%25e3%2583%25aa%25e3%2583%25bc%25e3%2580%25912026-6-29-fifa%25e3%2583%25af%25e3%2583%25bc%25e3%2583%25ab%25e3%2583%2589%25e3%2582%25ab%25e3%2583%2583%25e3%2583%25972026-%25e6%25b1%25ba%25e5%258b%259d%25e3%2583%2588%25e3%2583%25bc"
    },
    {
      "time": "2026-06-30T03:19:58+00:00",
      "title": "決勝Tで勝てない日本代表に足りないものは？ 「組織力」を高く評価も、各国のW杯経験者が指摘したブラジルとの差",
      "body": "ワールドサッカーダイジェスト",
      "tag": "ニュース",
      "url": "https://web.ultra-soccer.jp/news/all/27315/?utm_source=rss&utm_medium=rss&utm_campaign=%25e6%25b1%25ba%25e5%258b%259dt%25e3%2581%25a7%25e5%258b%259d%25e3%2581%25a6%25e3%2581%25aa%25e3%2581%2584%25e6%2597%25a5%25e6%259c%25ac%25e4%25bb%25a3%25e8%25a1%25a8%25e3%2581%25ab%25e8%25b6%25b3%25e3%2582%258a%25e3%2581%25aa%25e3%2581%2584%25e3%2582%2582%25e3%2581%25ae%25e3%2581%25af%25ef%25bc%259f-%25e3%2580%258c%25e7%25b5%2584"
    },
    {
      "time": "2026-06-30T02:30:33+00:00",
      "title": "“最高の景色”には届かずも…日本代表がW杯で示したチーム力、得点数や得点直接関与選手数は過去最多",
      "body": "ワールドサッカーダイジェスト",
      "tag": "ニュース",
      "url": "https://web.ultra-soccer.jp/news/all/27300/?utm_source=rss&utm_medium=rss&utm_campaign=%25e6%259c%2580%25e9%25ab%2598%25e3%2581%25ae%25e6%2599%25af%25e8%2589%25b2%25e3%2581%25ab%25e3%2581%25af%25e5%25b1%258a%25e3%2581%258b%25e3%2581%259a%25e3%2582%2582%25e6%2597%25a5%25e6%259c%25ac%25e4%25bb%25a3%25e8%25a1%25a8%25e3%2581%258cw%25e6%259d%25af%25e3%2581%25a7%25e7%25a4%25ba"
    }
  ],
  "en": [
    {
      "time": "2026-06-29T12:00:00Z",
      "title": "Full-time ⚽",
      "body": "Germany 1-1 Paraguay",
      "tag": "FULL-TIME"
    },
    {
      "time": "2026-06-29T12:00:00Z",
      "title": "Full-time ⚽",
      "body": "Netherlands 1-1 Morocco",
      "tag": "FULL-TIME"
    },
    {
      "time": "2026-06-29T12:00:00Z",
      "title": "Full-time ⚽",
      "body": "Brazil 2-1 Japan",
      "tag": "FULL-TIME"
    },
    {
      "time": "2026-06-28T12:00:00Z",
      "title": "Full-time ⚽",
      "body": "South Africa 0-1 Canada",
      "tag": "FULL-TIME"
    },
    {
      "time": "2026-06-27T12:00:00Z",
      "title": "Full-time ⚽",
      "body": "Algeria 3-3 Austria",
      "tag": "FULL-TIME"
    },
    {
      "time": "2026-06-27T12:00:00Z",
      "title": "Full-time ⚽",
      "body": "Jordan 1-3 Argentina",
      "tag": "FULL-TIME"
    },
    {
      "time": "2026-06-27T12:00:00Z",
      "title": "Full-time ⚽",
      "body": "Colombia 0-0 Portugal",
      "tag": "FULL-TIME"
    },
    {
      "time": "2026-06-27T12:00:00Z",
      "title": "Full-time ⚽",
      "body": "DR Congo 3-1 Uzbekistan",
      "tag": "FULL-TIME"
    },
    {
      "time": "2026-06-27T12:00:00Z",
      "title": "Full-time ⚽",
      "body": "Panama 0-2 England",
      "tag": "FULL-TIME"
    },
    {
      "time": "2026-06-27T12:00:00Z",
      "title": "Full-time ⚽",
      "body": "Croatia 2-1 Ghana",
      "tag": "FULL-TIME"
    },
    {
      "time": "2026-06-26T12:00:00Z",
      "title": "Full-time ⚽",
      "body": "Egypt 1-1 IR Iran",
      "tag": "FULL-TIME"
    },
    {
      "time": "2026-06-26T12:00:00Z",
      "title": "Full-time ⚽",
      "body": "New Zealand 1-5 Belgium",
      "tag": "FULL-TIME"
    }
  ]
}